explainer/__init__.py
explainer/datasets/__init__.py
explainer/datasets/_api.py
explainer/datasets/base.py
explainer/datasets/custom_clip.py
explainer/datasets/im2gps.py
explainer/datasets/imagenet.py
explainer/datasets/pascal.py
explainer/explanation_score.py
explainer/models/__init__.py
explainer/models/_api.py
explainer/models/_clip.py
explainer/models/_geo_estimator.py
explainer/models/_resnet.py
explainer/models/_segment_anything.py
explainer/models/_utils.py
explainer/models/_vit.py
explainer/models/base.py
explainer/models/object_model/prm/functions/__init__.py
explainer/models/object_model/prm/functions/peak_backprop.py
explainer/models/object_model/prm/functions/peak_stimulation.py
explainer/models/object_model/prm/modules/__init__.py
explainer/models/object_model/prm/modules/peak_response_mapping.py
explainer/models/object_model/prm/prm.py
explainer/models/object_model/prm/resnet.py
explainer/parts_extraction/__init__.py
explainer/parts_extraction/_lrp_utily.py
explainer/parts_extraction/extraction.py
explainer/parts_extraction/grabcut.py
explainer/parts_extraction/graph_partition.py
explainer/parts_extraction/relevancies.py
explainer/parts_extraction/segmentation.py
explainer/resources/__init__.py
explainer/resources/cell_partitionings/50_1000.csv
explainer/resources/cell_partitionings/50_2000.csv
explainer/resources/cell_partitionings/50_5000.csv
explainer/resources/cell_partitionings/__init__.py
explainer/resources/datasets/__init__.py
explainer/resources/datasets/imagenet_classes.txt
explainer/util/__init__.py
explainer/util/filehandling.py
explainer/util/functionalities.py
explainer/util/geo_estimator.py
explainer/util/hooks.py
explainer/util/return_types.py
explainer/util/segment_anything/__init__.py
explainer/util/segment_anything/automatic_mask_generator.py
explainer/util/segment_anything/build_sam.py
explainer/util/segment_anything/modeling/__init__.py
explainer/util/segment_anything/modeling/common.py
xai_explainer-0.7.0.dist-info/LICENSE
xai_explainer-0.7.0.dist-info/METADATA
xai_explainer-0.7.0.dist-info/WHEEL
xai_explainer-0.7.0.dist-info/RECORD
